fortfmt_fix-0.1.0.dist-info/licenses/LICENSE
fortran_format_codemod/__init__.py
fortran_format_codemod/cli.py
fortran_format_codemod/core.py
fortran_format_codemod/py.typed
fortfmt_fix-0.1.0.dist-info/METADATA
fortfmt_fix-0.1.0.dist-info/WHEEL
fortfmt_fix-0.1.0.dist-info/entry_points.txt
fortfmt_fix-0.1.0.dist-info/top_level.txt
fortfmt_fix-0.1.0.dist-info/RECORD
