Metadata-Version: 2.4
Name: fortfmt-fix
Version: 0.1.0
Summary: Codemod to replace Intel/DEC omitted-width FORMATs with standard-conforming Fortran I/O
Author-email: David Bross <brossdh@anl.gov>
License: BSD-3-Clause
Project-URL: Homepage, https://github.com/dbross/fortfmt-fix
Project-URL: Repository, https://github.com/dbross/fortfmt-fix
Project-URL: Issues, https://github.com/dbross/fortfmt-fix/issues
Keywords: fortran,compiler,modernization,portability,gfortran,intel,format
Classifier: License :: OSI Approved :: BSD License
Classifier: Programming Language :: Python :: 3
Classifier: Operating System :: OS Independent
Classifier: Topic :: Software Development :: Code Generators
Classifier: Intended Audience :: Science/Research
Requires-Python: >=3.9
License-File: LICENSE
Provides-Extra: dev
Requires-Dist: pytest>=7.0; extra == "dev"
Dynamic: license-file
